nephele/AwsAutoScalingGroup.py
nephele/AwsEni.py
nephele/AwsInstance.py
nephele/AwsLogGroup.py
nephele/AwsLogStream.py
nephele/AwsProcessor.py
nephele/AwsProcessorFactoryImpl.py
nephele/AwsRole.py
nephele/AwsRoot.py
nephele/AwsStack.py
nephele/CommandArgumentParser.py
nephele/Config.py
nephele/SilentException.py
nephele/SlashException.py
nephele/__init__.py
nephele/main.py
nephele-0.0.43.dist-info/DESCRIPTION.rst
nephele-0.0.43.dist-info/METADATA
nephele-0.0.43.dist-info/RECORD
nephele-0.0.43.dist-info/WHEEL
nephele-0.0.43.dist-info/entry_points.txt
nephele-0.0.43.dist-info/metadata.json
nephele-0.0.43.dist-info/top_level.txt
