Metadata-Version: 2.0
Name: nephele
Version: 0.0.43
Summary: A shell for AWS
Home-page: https://github.com/earlye/nephele
Author: Early Ehlinger
Author-email: earlye+nephele@gmail.com
License: MIT
Keywords: AWS usage
Platform: UNKNOWN
Classifier: Development Status :: 3 - Alpha
Classifier: Intended Audience :: Developers
Classifier: Topic :: System :: Shells
Classifier: License :: OSI Approved :: MIT License
Classifier: Programming Language :: Python :: 2
Classifier: Programming Language :: Python :: 2.7
Requires-Dist: awscli
Requires-Dist: boto3
Requires-Dist: gnureadline
Requires-Dist: joblib
Requires-Dist: pyperclip
Requires-Dist: stdplus
Requires-Dist: stdplusAwsHelpers
Provides-Extra: dev
Requires-Dist: check-manifest; extra == 'dev'
Provides-Extra: test
Requires-Dist: coverage; extra == 'test'
